LICENSE
MANIFEST.in
README.md
setup.py
powned/__init__.py
powned/api.py
powned/exceptions.py
powned/password.py
powned.egg-info/PKG-INFO
powned.egg-info/SOURCES.txt
powned.egg-info/dependency_links.txt
powned.egg-info/requires.txt
powned.egg-info/top_level.txt