Metadata-Version: 2.1
Name: powned
Version: 0.1.0
Summary: A python package allowing you to check if your password has been pwned.
Home-page: https://github.com/alexmacniven/powned
Author: Alex Macniven
Author-email: macniven.ap@gmail.com
License: MIT
Platform: UNKNOWN
Classifier: License :: OSI Approved :: MIT License
Classifier: Programming Language :: Python
Classifier: Programming Language :: Python :: 3
Classifier: Programming Language :: Python :: 3.7
Classifier: Programming Language :: Python :: Implementation :: CPython
Classifier: Programming Language :: Python :: Implementation :: PyPy
Requires-Python: >=3.7.0
Provides-Extra: dev
